LICENSE
README.md
setup.py
flipkart_product_scraper/__init__.py
flipkart_product_scraper.egg-info/PKG-INFO
flipkart_product_scraper.egg-info/SOURCES.txt
flipkart_product_scraper.egg-info/dependency_links.txt
flipkart_product_scraper.egg-info/requires.txt
flipkart_product_scraper.egg-info/top_level.txt