Metadata-Version: 2.1
Name: flipkart-product-scraper
Version: 1.0.2
Summary: A python library to scrape flipkart products
Home-page: UNKNOWN
Author: DataKund
Author-email: datakund@gmail.com
License: Apache License 2.0
Keywords: flipkart python bot_studio automation product scraper price title
Platform: UNKNOWN
License-File: LICENSE
